pterm/__init__.py
pterm/test_pterm.py
pterm/version.py
pterm-0.14.2.data/scripts/pterm
pterm-0.14.2.dist-info/LICENCE
pterm-0.14.2.dist-info/METADATA
pterm-0.14.2.dist-info/WHEEL
pterm-0.14.2.dist-info/top_level.txt
pterm-0.14.2.dist-info/RECORD
