Metadata-Version: 2.1
Name: pterm
Version: 0.14.2
Summary: Setup iterm2
Home-page: https://github.com/mhristof/pterm
Author: Mike Christof
Author-email: mhristof@gmail.com
License: UNKNOWN
Platform: UNKNOWN
Requires-Python: >=3.6
Requires-Dist: iterm2 (==1.9)
Requires-Dist: PyYAML (==5.3)
Requires-Dist: sh (==1.12.14)
